main.py
pagevecfind-0.0.1.dist-info/METADATA
pagevecfind-0.0.1.dist-info/WHEEL
pagevecfind-0.0.1.dist-info/entry_points.txt
pagevecfind-0.0.1.dist-info/top_level.txt
pagevecfind-0.0.1.dist-info/RECORD
