Metadata-Version: 2.4
Name: pagevecfind
Version: 0.0.1
Summary: Static-site vector embedding generator for PageVecFind
Author-email: Rikki <i@rikki.moe>
License: MIT
Project-URL: Homepage, https://github.com/rikkix/pagevecfind
Project-URL: Repository, https://github.com/rikkix/pagevecfind
Requires-Python: >=3.8
Requires-Dist: click>=8.0
Requires-Dist: sentence-transformers>=2.0
Requires-Dist: beautifulsoup4>=4.10
